Changelog.rst
Developer_Manual.rst
LICENSE.txt
MANIFEST.in
README.rst
pyproject.toml
setup.cfg
setup.py
SajadMr/Builtins.py
SajadMr/BytecodeCaching.py
SajadMr/Bytecodes.py
SajadMr/CacheCleanup.py
SajadMr/Constants.py
SajadMr/Errors.py
SajadMr/HardImportRegistry.py
SajadMr/MainControl.py
SajadMr/ModuleRegistry.py
SajadMr/OptionParsing.py
SajadMr/Options.py
SajadMr/OutputDirectories.py
SajadMr/PostProcessing.py
SajadMr/Progress.py
SajadMr/PythonFlavors.py
SajadMr/PythonOperators.py
SajadMr/PythonVersions.py
SajadMr/Serialization.py
SajadMr/SourceCodeReferences.py
SajadMr/Tracing.py
SajadMr/TreeXML.py
SajadMr/Variables.py
SajadMr/Version.py
SajadMr/__init__.py
SajadMr/__main__.py
SajadMr/__past__.py
SajadMr/build/Backend.scons
SajadMr/build/CCompilerVersion.scons
SajadMr/build/DataComposerInterface.py
SajadMr/build/Offsets.scons
SajadMr/build/Onefile.scons
SajadMr/build/SconsCaching.py
SajadMr/build/SconsCompilerSettings.py
SajadMr/build/SconsHacks.py
SajadMr/build/SconsInterface.py
SajadMr/build/SconsProgress.py
SajadMr/build/SconsSpawn.py
SajadMr/build/SconsUtils.py
SajadMr/build/__init__.py
SajadMr/build/include/SajadMr/allocator.h
SajadMr/build/include/SajadMr/builtins.h
SajadMr/build/include/SajadMr/calling.h
SajadMr/build/include/SajadMr/checkers.h
SajadMr/build/include/SajadMr/checksum_tools.h
SajadMr/build/include/SajadMr/compiled_asyncgen.h
SajadMr/build/include/SajadMr/compiled_cell.h
SajadMr/build/include/SajadMr/compiled_coroutine.h
SajadMr/build/include/SajadMr/compiled_frame.h
SajadMr/build/include/SajadMr/compiled_function.h
SajadMr/build/include/SajadMr/compiled_generator.h
SajadMr/build/include/SajadMr/compiled_method.h
SajadMr/build/include/SajadMr/constants.h
SajadMr/build/include/SajadMr/constants_blob.h
SajadMr/build/include/SajadMr/debug_settings.h
SajadMr/build/include/SajadMr/environment_variables.h
SajadMr/build/include/SajadMr/environment_variables_system.h
SajadMr/build/include/SajadMr/exception_groups.h
TEAM_SX.egg-info/PKG-INFO
TEAM_SX.egg-info/SOURCES.txt
TEAM_SX.egg-info/dependency_links.txt
TEAM_SX.egg-info/entry_points.txt
TEAM_SX.egg-info/not-zip-safe
TEAM_SX.egg-info/requires.txt
TEAM_SX.egg-info/top_level.txt
